{
  "BACK_ALLEY_HOUSE": "Castle Town",
  "BENEATH_THE_GRAVEYARD": "Ikana Road",
  "BENEATH_THE_WELL": "Ikana Canyon",
  "BLACKSMITH": "Mountain Village",
  "BOMB_SHOP": "West Clock Town",
  "BOMBCHU_BOWLING_ALLEY": "Castle Town",
  "BOTTOM_OF_THE_WELL": "Bottom of the Well",
  "CASTLE_COURTYARD": "Hyrule Castle",
  "CASTLE_IKANA": "Ikana Canyon",
  "CLOCK_TOWER_ROOFTOP": "South Clock Town",
  "CLOCK_TOWN_EAST": "East Clock Town",
  "CLOCK_TOWN_NORTH": "North Clock Town",
  "CLOCK_TOWN_SOUTH": "South Clock Town",
  "CLOCK_TOWN_WEST": "West Clock Town",
  "CUCCO_SHACK": "Romani Ranch",
  "CURIOSITY_SHOP": "West Clock Town",
  "DAMPE_HOUSE": "Ikana Road",
  "DEATH_MOUNTAIN_CRATER": "Death Mountain Crater",
  "DEATH_MOUNTAIN_TRAIL": "Death Mountain",
  "DEKU_KING_CHAMBER": "Deku Palace",
  "DEKU_PALACE": "Deku Palace",
  "DEKU_PLAYGROUND": "North Clock Town",
  "DEKU_SHRINE": "Deku Palace",
  "DESERT_COLOSSUS": "Desert Colossus",
  "DODONGO_CAVERN": "Dodongos Cavern",
  "DOG_RACETRACK": "Romani Ranch",
  "FAIRY_FOUNTAIN": "Fairy Fountain",
  "FISHING_POND": "Lake Hylia",
  "GANON_CASTLE_EXTERIOR": "Hyrule Castle",
  "GANON_TOWER": "Ganons Castle",
  "GERUDO_FORTRESS": "Gerudo Fortress",
  "GERUDO_TRAINING_GROUND": "Gerudo Training Grounds",
  "GERUDO_VALLEY": "Gerudo Valley",
  "GHOST_HUT": "Ikana Canyon",
  "GORMAN_TRACK": "Termina Field",
  "GORON_CITY": "Goron City",
  "GORON_GRAVEYARD": "Mountain Village",
  "GORON_RACETRACK": "Twin Islands",
  "GORON_SHRINE": "Goron Village",
  "GORON_VILLAGE_WINTER": "Goron Village",
  "GRAVEYARD": "Kakariko Graveyard",
  "GREAT_BAY_COAST": "Great Bay",
  "GREAT_FAIRY_FOUNTAIN_SPELLS": "Fairy Fountain",
  "GREAT_FAIRY_FOUNTAIN_UPGRADES": "Fairy Fountain",
  "GROTTOS": "Grotto",
  "GUARD_HOUSE": "Castle Town",
  "HAUNTED_WASTELAND": "Desert Colossus",
  "HONEY_DARLING": "East Clock Town",
  "HOUSE_OF_SKULLTULA": "Kakariko Village",
  "HYRULE_CASTLE": "Hyrule Castle",
  "HYRULE_FIELD": "Hyrule Field",
  "ICE_CAVERN": "Ice Cavern",
  "IKANA_CANYON": "Ikana Canyon",
  "IKANA_GRAVEYARD": "Ikana Road",
  "IMPA_HOUSE": "Kakariko Village",
  "INSIDE_DEKU_TREE": "Deku Tree",
  "INSIDE_GANON_CASTLE": "Ganons Castle",
  "INSIDE_JABU_JABU": "Jabu Jabu",
  "KAKARIKO_POTION_SHOP": "Kakariko Village",
  "KAKARIKO_VILLAGE": "Kakariko Village",
  "KOKIRI_FOREST": "Kokiri Forest",
  "KOKIRI_MIDO": "Kokiri Forest",
  "LABORATORY": "Great Bay",
  "LAIR_BARINADE": "Jabu Jabu",
  "LAIR_BONGO_BONGO": "Shadow Temple",
  "LAIR_GOHMA": "Deku Tree",
  "LAIR_GOHT": "Snowhead Temple",
  "LAIR_GYORG": "Great Bay Temple",
  "LAIR_IKANA": "Ikana Canyon",
  "LAIR_KING_DODONGO": "Dodongos Cavern",
  "LAIR_MORPHA": "Water Temple",
  "LAIR_ODOLWA": "Woodfall Temple",
  "LAIR_PHANTOM_GANON": "Forest Temple",
  "LAIR_TWINMOLD": "Stone Tower Temple",
  "LAIR_TWINROVA": "Spirit Temple",
  "LAIR_VOLVAGIA": "Fire Temple",
  "LAKE_HYLIA": "Lake Hylia",
  "LAUNDRY_POOL": "South Clock Town",
  "LON_LON_RANCH": "Lon Lon Ranch",
  "LOST_WOODS": "Lost Woods",
  "MAYOR_HOUSE": "East Clock Town",
  "MILK_BAR": "East Clock Town",
  "MOON_DEKU": "The Moon",
  "MOON_GORON": "The Moon",
  "MOON_LINK": "The Moon",
  "MOON_ZORA": "The Moon",
  "MOUNTAIN_VILLAGE_WINTER": "Mountain Village",
  "MUSIC_BOX_HOUSE": "Ikana Canyon",
  "OBSERVATORY": "Termina Field",
  "PATH_SNOWHEAD": "Snowhead",
  "PINNACLE_ROCK": "Great Bay",
  "PIRATE_FORTRESS_ENTRANCE": "Pirates Fortress",
  "PIRATE_FORTRESS_EXTERIOR": "Pirates Fortress",
  "PIRATE_FORTRESS_INTERIOR": "Pirates Fortress",
  "POST_OFFICE": "West Clock Town",
  "POTION_SHOP": "Southern Swamp",
  "RANCH_HOUSE_SILO": "Lon Lon Ranch",
  "ROAD_IKANA": "Ikana Road",
  "ROAD_SOUTHERN_SWAMP": "Southern Swamp",
  "ROMANI_RANCH": "Romani Ranch",
  "SACRED_FOREST_MEADOW": "Lost Woods",
  "SECRET_SHRINE": "Ikana Canyon",
  "SHOOTING_GALLERY": "East Clock Town",
  "SHOOTING_GALLERY_SWAMP": "Southern Swamp",
  "SOUTHERN_SWAMP": "Southern Swamp",
  "SPIDER_HOUSE_OCEAN": "Ocean Spider House",
  "SPIDER_HOUSE_SWAMP": "Swamp Spider House",
  "STOCK_POT_INN": "East Clock Town",
  "STONE_TOWER_INVERTED": "Stone Tower",
  "SWORDSMAN_SCHOOL": "West Clock Town",
  "TEMPLE_FIRE": "Fire Temple",
  "TEMPLE_FOREST": "Forest Temple",
  "TEMPLE_GREAT_BAY": "Great Bay Temple",
  "TEMPLE_OF_TIME": "Castle Town",
  "TEMPLE_SHADOW": "Shadow Temple",
  "TEMPLE_SNOWHEAD": "Snowhead Temple",
  "TEMPLE_SPIRIT": "Spirit Temple",
  "TEMPLE_STONE_TOWER": "Stone Tower Temple",
  "TEMPLE_WATER": "Water Temple",
  "TEMPLE_WOODFALL": "Woodfall Temple",
  "TERMINA_FIELD": "Termina Field",
  "THIEVES_HIDEOUT": "Gerudo Fortress",
  "TOMB_DAMPE_WINDMILL": "Kakariko Graveyard",
  "TOMB_FAIRY": "Kakariko Graveyard",
  "TOMB_REDEAD": "Kakariko Graveyard",
  "TOMB_ROYAL": "Kakariko Graveyard",
  "TOURIST_INFORMATION": "Southern Swamp",
  "TREASURE_SHOP": "East Clock Town",
  "TWIN_ISLANDS_WINTER": "Twin Islands",
  "WATERFALL_RAPIDS": "Zora Cap",
  "WOODFALL": "Woodfall",
  "ZORA_CAPE": "Zora Cape",
  "ZORA_DOMAIN": "Zoras Domain",
  "ZORA_FOUNTAIN": "Zoras Domain",
  "ZORA_HALL": "Zora Cape",
  "ZORA_HALL_ROOMS": "Zora Cape",
  "ZORA_RIVER": "Zoras River",
  "OOT Treasure Game HP": "Castle Town",
  "MM Chest Game HP": "East Clock Town",
  "MM Deku Palace Grotto Chest": "Deku Palace",
  "MM Great Bay Coast Fisherman Grotto": "Great Bay",
  "MM Ikana Graveyard Grotto": "Ikana Road",
  "MM Ikana Valley Grotto": "Ikana Canyon",
  "MM Lone Peak Shrine Boulder Chest": "Goron Village",
  "MM Lone Peak Shrine Invisible Chest": "Goron Village",
  "MM Lone Peak Shrine Lens Chest": "Goron Village",
  "MM Mountain Village Tunnel Grotto": "Mountain Village",
  "MM Path to Snowhead Grotto": "Snowhead",
  "MM Road to Ikana Grotto": "Ikana Road",
  "MM Road to Southern Swamp Grotto": "Southern Swamp",
  "MM Southern Swamp Grotto": "Southern Swamp",
  "MM Termina Field Bio Baba Grotto": "Termina Field",
  "MM Termina Field Dodongo Grotto": "Termina Field",
  "MM Termina Field Gossip Stones HP": "Termina Field",
  "MM Termina Field Peahat Grotto": "Termina Field",
  "MM Termina Field Pillar Grotto": "Termina Field",
  "MM Termina Field Scrub": "Termina Field",
  "MM Termina Field Tall Grass Grotto": "Termina Field",
  "MM Twin Islands Frozen Grotto Chest": "Twin Islands",
  "MM Twin Islands Ramp Grotto Chest": "Twin Islands",
  "MM Woods of Mystery Grotto": "Southern Swamp",
  "MM Zora Cape Grotto": "Zora Cape",
  "OOT Death Mountain Crater Grotto": "Death Mountain Crater",
  "OOT Death Mountain Grotto": "Death Mountain",
  "OOT Deku Theater Nuts Upgrade": "Lost Woods",
  "OOT Deku Theater Sticks Upgrade": "Lost Woods",
  "OOT Hyrule Castle GS Grotto": "Hyrule Castle",
  "OOT Hyrule Field Grotto Market": "Hyrule Field",
  "OOT Hyrule Field Grotto Near Gerudo GS": "Hyrule Field",
  "OOT Hyrule Field Grotto Near Kakariko GS": "Hyrule Field",
  "OOT Hyrule Field Grotto Open": "Hyrule Field",
  "OOT Hyrule Field Grotto Scrub HP": "Hyrule Field",
  "OOT Hyrule Field Grotto Southeast": "Hyrule Field",
  "OOT Hyrule Field Grotto Tektite HP": "Hyrule Field",
  "OOT Kakariko Grotto Back": "Kakariko Village",
  "OOT Kakariko Grotto Front": "Kakariko Village",
  "OOT Kokiri Forest Storms Grotto": "Kokiri Forest",
  "OOT Lost Woods Grotto Generic": "Lost Woods",
  "OOT Lost Woods Grotto Scrub Nuts Upgrade": "Lost Woods",
  "OOT Sacred Meadow Grotto": "Lost Woods",
  "OOT Zora River Grotto": "Zoras River",
  "MM Clock Town Great Fairy": "North Clock Town",
  "MM Clock Town Great Fairy Alt": "North Clock Town",
  "MM Great Bay Great Fairy": "Great Bay",
  "MM Ikana Great Fairy": "Ikana Canyon",
  "MM Snowhead Great Fairy": "Snowhead",
  "MM Woodfall Great Fairy": "Woodfall",
  "OOT Great Fairy Defense Upgrade": "Hyrule Castle",
  "OOT Great Fairy Din's Fire": "Hyrule Castle",
  "OOT Great Fairy Farore's Wind": "Zoras Domain",
  "OOT Great Fairy Magic Upgrade": "Death Mountain",
  "OOT Great Fairy Magic Upgrade 2": "Death Mountain Crater",
  "OOT Great Fairy Nayru's Love": "Desert Colossus",
  "OOT Laboratory Dive": "Lake Hylia",
  "OOT Laboratory Eye Drops": "Lake Hylia",
  "OOT Laboratory GS Crate": "Lake Hylia",
  "MM Laboratory Zora Song": "Great Bay",
  "MM Laboratory Fish HP": "Great Bay",
  "MM Town Archery Reward 1": "East Clock Town",
  "MM Town Archery Reward 2": "East Clock Town",
  "OOT Shooting Gallery Child": "Castle Town",
  "OOT Shooting Gallery Adult": "Kakariko Village"
}
